stix_shifter_modules/infoblox/__init__.py
stix_shifter_modules/infoblox/entry_point.py
stix_shifter_modules/infoblox/configuration/config.json
stix_shifter_modules/infoblox/configuration/dialects.json
stix_shifter_modules/infoblox/configuration/lang_en.json
stix_shifter_modules/infoblox/stix_translation/__init__.py
stix_shifter_modules/infoblox/stix_translation/json_to_stix_translator.py
stix_shifter_modules/infoblox/stix_translation/query_constructor.py
stix_shifter_modules/infoblox/stix_translation/query_translator.py
stix_shifter_modules/infoblox/stix_translation/transformers.py
stix_shifter_modules/infoblox/stix_translation/json/dnsEventData_from_stix_map.json
stix_shifter_modules/infoblox/stix_translation/json/dnsEventData_operators.json
stix_shifter_modules/infoblox/stix_translation/json/dossierData_from_stix_map.json
stix_shifter_modules/infoblox/stix_translation/json/dossierData_operators.json
stix_shifter_modules/infoblox/stix_translation/json/tideDbData_from_stix_map.json
stix_shifter_modules/infoblox/stix_translation/json/tideDbData_operators.json
stix_shifter_modules/infoblox/stix_translation/json/to_stix_map.json
stix_shifter_modules/infoblox/stix_transmission/__init__.py
stix_shifter_modules/infoblox/stix_transmission/api_client.py
stix_shifter_modules/infoblox/stix_transmission/delete_connector.py
stix_shifter_modules/infoblox/stix_transmission/error_mapper.py
stix_shifter_modules/infoblox/stix_transmission/ping_connector.py
stix_shifter_modules/infoblox/stix_transmission/query_connector.py
stix_shifter_modules/infoblox/stix_transmission/results_connector.py
stix_shifter_modules/infoblox/stix_transmission/status_connector.py
stix_shifter_modules/infoblox/test/stix_translation/test_stix_to_query_parsing.json
stix_shifter_modules_infoblox-8.0.2.dist-info/licenses/AUTHORS.md
stix_shifter_modules_infoblox-8.0.2.dist-info/licenses/LICENSE.md
stix_shifter_modules_infoblox-8.0.2.dist-info/licenses/NOTICE
stix_shifter_modules_infoblox-8.0.2.dist-info/METADATA
stix_shifter_modules_infoblox-8.0.2.dist-info/WHEEL
stix_shifter_modules_infoblox-8.0.2.dist-info/top_level.txt
stix_shifter_modules_infoblox-8.0.2.dist-info/RECORD
